xbutils/__init__.py
xbutils/cmd.py
xbutils/htmlwriter.py
xbutils/log.py
xbutils/simple_config.py
xbutils/template.py
xbutils/textupdater.py
xbutils-0.9.3.dist-info/LICENSE
xbutils-0.9.3.dist-info/METADATA
xbutils-0.9.3.dist-info/WHEEL
xbutils-0.9.3.dist-info/top_level.txt
xbutils-0.9.3.dist-info/RECORD
