Metadata-Version: 2.1
Name: xbutils
Version: 0.9.3
Summary: Python utilities
Home-page: https://github.com/exbee49/xbutils
Author: xb49
Author-email: 
License: WTFPL
Classifier: Development Status :: 4 - Beta
Classifier: Programming Language :: Python :: 3 :: Only
License-File: LICENSE
